django_dkron-1.2.3.dist-info/licenses/LICENSE
dkron/__init__.py
dkron/admin.py
dkron/apps.py
dkron/forms.py
dkron/models.py
dkron/urls.py
dkron/urls_api.py
dkron/utils.py
dkron/views.py
dkron/management/__init__.py
dkron/management/commands/__init__.py
dkron/management/commands/cleanup_dkron.py
dkron/management/commands/resync_dkron.py
dkron/management/commands/run_dkron.py
dkron/management/commands/run_dkron_async_command.py
dkron/migrations/0001_initial_20210729.py
dkron/migrations/0002_job_retries.py
dkron/migrations/0003_alter_job_schedule.py
dkron/migrations/__init__.py
dkron/templates/admin/dkron/job/change_list_object_tools.html
dkron/templatetags/__init__.py
dkron/templatetags/dkron.py
django_dkron-1.2.3.dist-info/METADATA
django_dkron-1.2.3.dist-info/WHEEL
django_dkron-1.2.3.dist-info/top_level.txt
django_dkron-1.2.3.dist-info/RECORD
