Metadata-Version: 2.4
Name: django-dkron
Version: 1.2.3
Summary: Manage and run jobs in Dkron from your django project
Home-page: https://github.com/surface-security/django-dkron
Author: PPB - InfoSec Engineering
Author-email: surface@paddypowerbetfair.com
License: MIT
Classifier: Development Status :: 5 - Production/Stable
Classifier: Framework :: Django
Classifier: License :: OSI Approved :: MIT License
Classifier: Intended Audience :: Developers
Classifier: Operating System :: OS Independent
Classifier: Programming Language :: Python
Classifier: Programming Language :: Python :: 3.9
Classifier: Environment :: Web Environment
Classifier: Topic :: Software Development
Requires-Python: >=3.9
License-File: LICENSE
Requires-Dist: Django<6,>=3.0
Requires-Dist: django-logbasecommand<1
Requires-Dist: django-notification-sender<2
Requires-Dist: requests<3,>2
Requires-Dist: django-after-response==0.2.2
Dynamic: license-file
